{
  "country": "Belize",
  "countryCode": "Q242",
  "generated": "2025-12-14T21:01:13.220Z",
  "rankingMetric": "sitelinks",
  "people": [
    {
      "id": 1,
      "name": "Simone Biles",
      "image": "http://commons.wikimedia.org/wiki/Special:FilePath/Simone%20Biles%20Rio%202016b.jpg",
      "sitelinks": 68,
      "birthYear": "1997",
      "deathYear": null,
      "occupation": "artistic gymnast",
      "wikidataUrl": "http://www.wikidata.org/entity/Q7520267",
      "answerKey": "simone biles",
      "wikipediaUrl": "https://en.wikipedia.org/wiki/Simone_Biles"
    },
    {
      "id": 2,
      "name": "Marion Jones",
      "image": "http://commons.wikimedia.org/wiki/Special:FilePath/Marion%20Jones%20Sydney%202000.JPEG",
      "sitelinks": 49,
      "birthYear": "1975",
      "deathYear": null,
      "occupation": "sprinter",
      "wikidataUrl": "http://www.wikidata.org/entity/Q209396",
      "answerKey": "marion jones",
      "wikipediaUrl": "https://en.wikipedia.org/wiki/Marion_Jones"
    },
    {
      "id": 3,
      "name": "Dean Barrow",
      "image": "http://commons.wikimedia.org/wiki/Special:FilePath/Belizean%20Prime%20Minister%2C%20Dean%20Barrow%20in%20London%2C%2027%20June%202013%20%28cropped%29.jpg",
      "sitelinks": 43,
      "birthYear": "1951",
      "deathYear": null,
      "occupation": "politician",
      "wikidataUrl": "http://www.wikidata.org/entity/Q57701",
      "answerKey": "dean barrow",
      "wikipediaUrl": "https://en.wikipedia.org/wiki/Dean_Barrow"
    },
    {
      "id": 4,
      "name": "Johnny Briceño",
      "image": "http://commons.wikimedia.org/wiki/Special:FilePath/Johnny%20Brice%C3%B1o%20%2852135383761%29%20%28cropped%29.jpg",
      "sitelinks": 34,
      "birthYear": "1960",
      "deathYear": null,
      "occupation": "politician",
      "wikidataUrl": "http://www.wikidata.org/entity/Q6266369",
      "answerKey": "johnny briceno",
      "wikipediaUrl": "https://en.wikipedia.org/wiki/Johnny_Brice%C3%B1o"
    },
    {
      "id": 5,
      "name": "George Cadle Price",
      "image": "http://commons.wikimedia.org/wiki/Special:FilePath/George%20Cadle%20Price.jpg",
      "sitelinks": 31,
      "birthYear": "1919",
      "deathYear": "2011",
      "occupation": "politician",
      "wikidataUrl": "http://www.wikidata.org/entity/Q542559",
      "answerKey": "george cadle price",
      "wikipediaUrl": "https://en.wikipedia.org/wiki/George_Cadle_Price"
    },
    {
      "id": 6,
      "name": "Said Musa",
      "image": "http://commons.wikimedia.org/wiki/Special:FilePath/Said%20Musa%202007.jpg",
      "sitelinks": 29,
      "birthYear": "1944",
      "deathYear": null,
      "occupation": "politician",
      "wikidataUrl": "http://www.wikidata.org/entity/Q335215",
      "answerKey": "said musa",
      "wikipediaUrl": "https://en.wikipedia.org/wiki/Said_Musa"
    },
    {
      "id": 7,
      "name": "Froyla Tzalam",
      "image": "http://commons.wikimedia.org/wiki/Special:FilePath/Dame%20Froyla%20Tzalam.jpg",
      "sitelinks": 25,
      "birthYear": "1971",
      "deathYear": null,
      "occupation": "anthropologist",
      "wikidataUrl": "http://www.wikidata.org/entity/Q106601151",
      "answerKey": "froyla tzalam",
      "wikipediaUrl": "https://en.wikipedia.org/wiki/Froyla_Tzalam"
    },
    {
      "id": 8,
      "name": "Colville Young",
      "image": "http://commons.wikimedia.org/wiki/Special:FilePath/Colville%20Young%20Embassy%202011%20%28cropped%29.jpeg",
      "sitelinks": 24,
      "birthYear": "1932",
      "deathYear": null,
      "occupation": "novelist",
      "wikidataUrl": "http://www.wikidata.org/entity/Q373552",
      "answerKey": "colville young",
      "wikipediaUrl": "https://en.wikipedia.org/wiki/Colville_Young"
    },
    {
      "id": 9,
      "name": "Manuel Esquivel",
      "image": "http://commons.wikimedia.org/wiki/Special:FilePath/Manuel%20Esquivel.jpg",
      "sitelinks": 23,
      "birthYear": "1940",
      "deathYear": "2022",
      "occupation": "politician",
      "wikidataUrl": "http://www.wikidata.org/entity/Q951969",
      "answerKey": "manuel esquivel",
      "wikipediaUrl": "https://en.wikipedia.org/wiki/Manuel_Esquivel"
    },
    {
      "id": 10,
      "name": "Arlen Escarpeta",
      "image": "http://commons.wikimedia.org/wiki/Special:FilePath/Arlen%20Escarpeta%202014%20%28cropped%29.jpg",
      "sitelinks": 16,
      "birthYear": "1980",
      "deathYear": null,
      "occupation": "film actor",
      "wikidataUrl": "http://www.wikidata.org/entity/Q957454",
      "answerKey": "arlen escarpeta",
      "wikipediaUrl": "https://en.wikipedia.org/wiki/Arlen_Escarpeta"
    },
    {
      "id": 11,
      "name": "Arlen Escarpeta",
      "image": "http://commons.wikimedia.org/wiki/Special:FilePath/Arlen%20Escarpeta%202014%20%28cropped%29.jpg",
      "sitelinks": 16,
      "birthYear": "1981",
      "deathYear": null,
      "occupation": "film actor",
      "wikidataUrl": "http://www.wikidata.org/entity/Q957454",
      "answerKey": "arlen escarpeta",
      "wikipediaUrl": "https://en.wikipedia.org/wiki/Arlen_Escarpeta"
    },
    {
      "id": 12,
      "name": "Milt Palacio",
      "image": "http://commons.wikimedia.org/wiki/Special:FilePath/Palacio%20USMC-051017-M-1525C-002%20%28cropped%29.jpg",
      "sitelinks": 14,
      "birthYear": "1978",
      "deathYear": null,
      "occupation": "basketball coach",
      "wikidataUrl": "http://www.wikidata.org/entity/Q2449958",
      "answerKey": "milt palacio",
      "wikipediaUrl": "https://en.wikipedia.org/wiki/Milt_Palacio"
    },
    {
      "id": 13,
      "name": "Shyne",
      "image": "http://commons.wikimedia.org/wiki/Special:FilePath/Shyne%20profile%20%28cropped%29.jpg",
      "sitelinks": 14,
      "birthYear": "1978",
      "deathYear": null,
      "occupation": "hip-hop musician",
      "wikidataUrl": "http://www.wikidata.org/entity/Q1346832",
      "answerKey": "shyne",
      "wikipediaUrl": "https://en.wikipedia.org/wiki/Shyne"
    },
    {
      "id": 14,
      "name": "Debra Baptist-Estrada",
      "image": "http://commons.wikimedia.org/wiki/Special:FilePath/Debra%20Baptist-Estrada%20of%20Belize.jpg",
      "sitelinks": 13,
      "birthYear": "2000",
      "deathYear": null,
      "occupation": "official",
      "wikidataUrl": "http://www.wikidata.org/entity/Q25350042",
      "answerKey": "debra baptistestrada",
      "wikipediaUrl": "https://en.wikipedia.org/wiki/Debra_Baptist-Estrada"
    },
    {
      "id": 15,
      "name": "Andy Palacio",
      "image": "http://commons.wikimedia.org/wiki/Special:FilePath/Andy%20Palacio.jpg",
      "sitelinks": 12,
      "birthYear": "1960",
      "deathYear": "2008",
      "occupation": "musician",
      "wikidataUrl": "http://www.wikidata.org/entity/Q278024",
      "answerKey": "andy palacio",
      "wikipediaUrl": "https://en.wikipedia.org/wiki/Andy_Palacio"
    },
    {
      "id": 16,
      "name": "Kenneth Medwood",
      "image": "http://commons.wikimedia.org/wiki/Special:FilePath/Kenneth%20Medwood.jpg",
      "sitelinks": 12,
      "birthYear": "1987",
      "deathYear": null,
      "occupation": "athletics competitor",
      "wikidataUrl": "http://www.wikidata.org/entity/Q540569",
      "answerKey": "kenneth medwood",
      "wikipediaUrl": "https://en.wikipedia.org/wiki/Kenneth_Medwood"
    },
    {
      "id": 17,
      "name": "Wilfred Elrington",
      "image": "http://commons.wikimedia.org/wiki/Special:FilePath/Wilfred%20Peter%20Elrington%20%28cropped%29.jpg",
      "sitelinks": 10,
      "birthYear": "1948",
      "deathYear": null,
      "occupation": "journalist",
      "wikidataUrl": "http://www.wikidata.org/entity/Q58325",
      "answerKey": "wilfred elrington",
      "wikipediaUrl": "https://en.wikipedia.org/wiki/Wilfred_Elrington"
    },
    {
      "id": 18,
      "name": "Errollyn Wallen",
      "image": "http://commons.wikimedia.org/wiki/Special:FilePath/ErrollynWallen%20%28cropped%29.png",
      "sitelinks": 10,
      "birthYear": "1958",
      "deathYear": null,
      "occupation": "pianist",
      "wikidataUrl": "http://www.wikidata.org/entity/Q5395651",
      "answerKey": "errollyn wallen",
      "wikipediaUrl": "https://en.wikipedia.org/wiki/Errollyn_Wallen"
    },
    {
      "id": 19,
      "name": "Woodrow West",
      "image": "http://commons.wikimedia.org/wiki/Special:FilePath/Woodrow%20West.jpg",
      "sitelinks": 10,
      "birthYear": "1985",
      "deathYear": null,
      "occupation": "association football player",
      "wikidataUrl": "http://www.wikidata.org/entity/Q6168227",
      "answerKey": "woodrow west",
      "wikipediaUrl": "https://en.wikipedia.org/wiki/Woodrow_West"
    },
    {
      "id": 20,
      "name": "Sharon Matola",
      "image": "http://commons.wikimedia.org/wiki/Special:FilePath/Sharon%20Matola%20at%20the%20Belize%20Zoo%2C%202011-07-20%20%28TBZ-3558%29.jpg",
      "sitelinks": 9,
      "birthYear": "1954",
      "deathYear": "2021",
      "occupation": "environmentalist",
      "wikidataUrl": "http://www.wikidata.org/entity/Q7490147",
      "answerKey": "sharon matola",
      "wikipediaUrl": "https://en.wikipedia.org/wiki/Sharon_Matola"
    },
    {
      "id": 21,
      "name": "Lawrence Sydney Nicasio",
      "image": "http://commons.wikimedia.org/wiki/Special:FilePath/Bishop%20Nicasio%202%20%28cropped%29.jpg",
      "sitelinks": 9,
      "birthYear": "1956",
      "deathYear": "2024",
      "occupation": "Catholic deacon",
      "wikidataUrl": "http://www.wikidata.org/entity/Q28529584",
      "answerKey": "lawrence sydney nicasio",
      "wikipediaUrl": "https://en.wikipedia.org/wiki/Lawrence_Sydney_Nicasio"
    },
    {
      "id": 22,
      "name": "Charles García",
      "image": "http://commons.wikimedia.org/wiki/Special:FilePath/Charles%20garcia%20basketball.jpg",
      "sitelinks": 9,
      "birthYear": "1988",
      "deathYear": null,
      "occupation": "basketball player",
      "wikidataUrl": "http://www.wikidata.org/entity/Q2690280",
      "answerKey": "charles garcia",
      "wikipediaUrl": "https://en.wikipedia.org/wiki/Charles_Garc%C3%ADa"
    },
    {
      "id": 23,
      "name": "Francis Fonseca",
      "image": "http://commons.wikimedia.org/wiki/Special:FilePath/Francis%20Fonseca%202022.jpg",
      "sitelinks": 9,
      "birthYear": "1967",
      "deathYear": null,
      "occupation": "politician",
      "wikidataUrl": "http://www.wikidata.org/entity/Q5480967",
      "answerKey": "francis fonseca",
      "wikipediaUrl": "https://en.wikipedia.org/wiki/Francis_Fonseca"
    },
    {
      "id": 24,
      "name": "Brandon Jones",
      "image": "http://commons.wikimedia.org/wiki/Special:FilePath/Brandon%20Jones%20Rio2016.jpg",
      "sitelinks": 9,
      "birthYear": "1987",
      "deathYear": null,
      "occupation": "athletics competitor",
      "wikidataUrl": "http://www.wikidata.org/entity/Q26611932",
      "answerKey": "brandon jones",
      "wikipediaUrl": "https://en.wikipedia.org/wiki/Brandon_Jones_(athlete)"
    },
    {
      "id": 25,
      "name": "Shaun Gill",
      "image": "http://commons.wikimedia.org/wiki/Special:FilePath/Shaun%20Gill%20Paris%202024.jpg",
      "sitelinks": 9,
      "birthYear": "1993",
      "deathYear": null,
      "occupation": "sprinter",
      "wikidataUrl": "http://www.wikidata.org/entity/Q50419666",
      "answerKey": "shaun gill",
      "wikipediaUrl": "https://en.wikipedia.org/wiki/Shaun_Gill"
    },
    {
      "id": 26,
      "name": "Kaina Martinez",
      "image": "http://commons.wikimedia.org/wiki/Special:FilePath/Kaina%20Martinez.jpg",
      "sitelinks": 8,
      "birthYear": "1986",
      "deathYear": null,
      "occupation": "athletics competitor",
      "wikidataUrl": "http://www.wikidata.org/entity/Q6348070",
      "answerKey": "kaina martinez",
      "wikipediaUrl": "https://en.wikipedia.org/wiki/Kaina_Martinez"
    },
    {
      "id": 27,
      "name": "Leon Williams",
      "image": "http://commons.wikimedia.org/wiki/Special:FilePath/02.LeonWilliams.jpg",
      "sitelinks": 8,
      "birthYear": "1986",
      "deathYear": null,
      "occupation": "basketball player",
      "wikidataUrl": "http://www.wikidata.org/entity/Q6524951",
      "answerKey": "leon williams",
      "wikipediaUrl": "https://en.wikipedia.org/wiki/Leon_Williams_(basketball%2C_born_1986)"
    },
    {
      "id": 28,
      "name": "Stuart Leslie",
      "image": "http://commons.wikimedia.org/wiki/Special:FilePath/Stuart%20Leslie%202022.jpg",
      "sitelinks": 8,
      "birthYear": "1964",
      "deathYear": null,
      "occupation": "diplomat",
      "wikidataUrl": "http://www.wikidata.org/entity/Q7626757",
      "answerKey": "stuart leslie",
      "wikipediaUrl": "https://en.wikipedia.org/wiki/Stuart_Leslie"
    },
    {
      "id": 29,
      "name": "Zee Edgell",
      "image": "http://commons.wikimedia.org/wiki/Special:FilePath/Zee%20edgell%20250.jpg",
      "sitelinks": 7,
      "birthYear": "1940",
      "deathYear": "2020",
      "occupation": "novelist",
      "wikidataUrl": "http://www.wikidata.org/entity/Q8068403",
      "answerKey": "zee edgell",
      "wikipediaUrl": "https://en.wikipedia.org/wiki/Zee_Edgell"
    },
    {
      "id": 30,
      "name": "Lisa Shoman",
      "image": "http://commons.wikimedia.org/wiki/Special:FilePath/Lisa%20Shoman%202015%20%28cropped%29.jpg",
      "sitelinks": 7,
      "birthYear": "1964",
      "deathYear": null,
      "occupation": "jurist",
      "wikidataUrl": "http://www.wikidata.org/entity/Q518511",
      "answerKey": "lisa shoman",
      "wikipediaUrl": "https://en.wikipedia.org/wiki/Lisa_Shoman"
    },
    {
      "id": 31,
      "name": "Joy Grant",
      "image": "http://commons.wikimedia.org/wiki/Special:FilePath/A%20Joy%20Grant.jpg",
      "sitelinks": 7,
      "birthYear": "1951",
      "deathYear": null,
      "occupation": "ambassador",
      "wikidataUrl": "http://www.wikidata.org/entity/Q18978033",
      "answerKey": "joy grant",
      "wikipediaUrl": "https://en.wikipedia.org/wiki/Joy_Grant"
    },
    {
      "id": 32,
      "name": "Tony Rocha",
      "image": "http://commons.wikimedia.org/wiki/Special:FilePath/CINvOCB%202017-05-13%20-%20Tony%20Rocha%20%2834494682032%29%20%28cropped%29.jpg",
      "sitelinks": 7,
      "birthYear": "1993",
      "deathYear": null,
      "occupation": "association football player",
      "wikidataUrl": "http://www.wikidata.org/entity/Q19901615",
      "answerKey": "tony rocha",
      "wikipediaUrl": "https://en.wikipedia.org/wiki/Tony_Rocha"
    },
    {
      "id": 33,
      "name": "Carla Barnett",
      "image": "http://commons.wikimedia.org/wiki/Special:FilePath/Carla%20Barnett%20-%2051551445678%20%28cropped%29.jpg",
      "sitelinks": 7,
      "birthYear": "1958",
      "deathYear": null,
      "occupation": "economist",
      "wikidataUrl": "http://www.wikidata.org/entity/Q86004208",
      "answerKey": "carla barnett",
      "wikipediaUrl": "https://en.wikipedia.org/wiki/Carla_Barnett"
    },
    {
      "id": 34,
      "name": "Phillip Goldson",
      "image": "http://commons.wikimedia.org/wiki/Special:FilePath/Philip%20Goldson%201965%20%28cropped%29.jpg",
      "sitelinks": 6,
      "birthYear": "1923",
      "deathYear": "2001",
      "occupation": "journalist",
      "wikidataUrl": "http://www.wikidata.org/entity/Q7185683",
      "answerKey": "phillip goldson",
      "wikipediaUrl": "https://en.wikipedia.org/wiki/Philip_Goldson"
    },
    {
      "id": 35,
      "name": "Sylvia Flores",
      "image": "http://commons.wikimedia.org/wiki/Special:FilePath/Minister%20Sylvia%20Flores%20%28cropped%29.jpg",
      "sitelinks": 6,
      "birthYear": "1951",
      "deathYear": "2022",
      "occupation": "Prime Minister of Belize",
      "wikidataUrl": "http://www.wikidata.org/entity/Q27943427",
      "answerKey": "sylvia flores",
      "wikipediaUrl": "https://en.wikipedia.org/wiki/Sylvia_Flores"
    },
    {
      "id": 36,
      "name": "Eddermys Sanchez",
      "image": "http://commons.wikimedia.org/wiki/Special:FilePath/Eddermys%20Sanchez.jpg",
      "sitelinks": 6,
      "birthYear": "1980",
      "deathYear": null,
      "occupation": "judoka",
      "wikidataUrl": "http://www.wikidata.org/entity/Q2107387",
      "answerKey": "eddermys sanchez",
      "wikipediaUrl": "https://en.wikipedia.org/wiki/Eddermys_Sanchez"
    },
    {
      "id": 37,
      "name": "Patrick Faber",
      "image": "http://commons.wikimedia.org/wiki/Special:FilePath/Patrick%20Faber%20%28cropped%29.jpg",
      "sitelinks": 6,
      "birthYear": "1978",
      "deathYear": null,
      "occupation": "politician",
      "wikidataUrl": "http://www.wikidata.org/entity/Q7146470",
      "answerKey": "patrick faber",
      "wikipediaUrl": "https://en.wikipedia.org/wiki/Patrick_Faber_(politician)"
    },
    {
      "id": 38,
      "name": "Luis Torres",
      "image": "http://commons.wikimedia.org/wiki/Special:FilePath/Luis%20Baca%20Torres.JPG",
      "sitelinks": 6,
      "birthYear": "1993",
      "deathYear": null,
      "occupation": "association football player",
      "wikidataUrl": "http://www.wikidata.org/entity/Q16573201",
      "answerKey": "luis torres",
      "wikipediaUrl": null
    },
    {
      "id": 39,
      "name": "Eamon Courtenay",
      "image": "http://commons.wikimedia.org/wiki/Special:FilePath/Eamon%20Courtenay%20%28cropped%29.jpg",
      "sitelinks": 5,
      "birthYear": "1960",
      "deathYear": null,
      "occupation": "politician",
      "wikidataUrl": "http://www.wikidata.org/entity/Q3046363",
      "answerKey": "eamon courtenay",
      "wikipediaUrl": "https://en.wikipedia.org/wiki/Eamon_Courtenay"
    },
    {
      "id": 40,
      "name": "Justin Williams",
      "image": "http://commons.wikimedia.org/wiki/Special:FilePath/JUSWilliamsWIKIPEDIA2.jpg",
      "sitelinks": 5,
      "birthYear": "1989",
      "deathYear": null,
      "occupation": "sport cyclist",
      "wikidataUrl": "http://www.wikidata.org/entity/Q1714240",
      "answerKey": "justin williams",
      "wikipediaUrl": "https://en.wikipedia.org/wiki/Justin_Williams_(cyclist)"
    },
    {
      "id": 41,
      "name": "Zenaida Moya",
      "image": "http://commons.wikimedia.org/wiki/Special:FilePath/Zenaida%20Moya%20%28cropped%29.jpg",
      "sitelinks": 5,
      "birthYear": "2000",
      "deathYear": null,
      "occupation": "politician",
      "wikidataUrl": "http://www.wikidata.org/entity/Q8069006",
      "answerKey": "zenaida moya",
      "wikipediaUrl": "https://en.wikipedia.org/wiki/Zenaida_Moya"
    },
    {
      "id": 42,
      "name": "Aishah Sutherland",
      "image": "http://commons.wikimedia.org/wiki/Special:FilePath/Aishah%20Sutherland.jpg",
      "sitelinks": 5,
      "birthYear": "1990",
      "deathYear": null,
      "occupation": "basketball player",
      "wikidataUrl": "http://www.wikidata.org/entity/Q15059102",
      "answerKey": "aishah sutherland",
      "wikipediaUrl": null
    },
    {
      "id": 43,
      "name": "Lois Michele Young",
      "image": "http://commons.wikimedia.org/wiki/Special:FilePath/Lois%20Michele%20Young%20%282013%29%20%28cropped%29.jpg",
      "sitelinks": 5,
      "birthYear": "1951",
      "deathYear": null,
      "occupation": "diplomat",
      "wikidataUrl": "http://www.wikidata.org/entity/Q16151601",
      "answerKey": "lois michele young",
      "wikipediaUrl": "https://en.wikipedia.org/wiki/Lois_Michele_Young"
    },
    {
      "id": 44,
      "name": "Rakeem Nunez-Roches",
      "image": "http://commons.wikimedia.org/wiki/Special:FilePath/Rakeem%20Nu%C3%B1ez-Roches.JPG",
      "sitelinks": 5,
      "birthYear": "1993",
      "deathYear": null,
      "occupation": "American football player",
      "wikidataUrl": "http://www.wikidata.org/entity/Q19893722",
      "answerKey": "rakeem nunezroches",
      "wikipediaUrl": "https://en.wikipedia.org/wiki/Rakeem_Nu%C3%B1ez-Roches"
    },
    {
      "id": 45,
      "name": "Caleb Orozco",
      "image": "http://commons.wikimedia.org/wiki/Special:FilePath/Caleb%20Orozco.jpg",
      "sitelinks": 5,
      "birthYear": "1973",
      "deathYear": null,
      "occupation": "human rights defender",
      "wikidataUrl": "http://www.wikidata.org/entity/Q27970206",
      "answerKey": "caleb orozco",
      "wikipediaUrl": "https://en.wikipedia.org/wiki/Caleb_Orozco"
    },
    {
      "id": 46,
      "name": "Ian Gray",
      "image": "http://commons.wikimedia.org/wiki/Special:FilePath/Ian%20Gray.jpg",
      "sitelinks": 5,
      "birthYear": "1963",
      "deathYear": null,
      "occupation": "athlete",
      "wikidataUrl": "http://www.wikidata.org/entity/Q43379550",
      "answerKey": "ian gray",
      "wikipediaUrl": "https://en.wikipedia.org/wiki/Ian_Gray_(runner)"
    },
    {
      "id": 47,
      "name": "Tracy Panton",
      "image": "http://commons.wikimedia.org/wiki/Special:FilePath/Tracy%20Panton%20%28cropped%29.jpg",
      "sitelinks": 5,
      "birthYear": "1969",
      "deathYear": null,
      "occupation": "politician",
      "wikidataUrl": "http://www.wikidata.org/entity/Q58896015",
      "answerKey": "tracy panton",
      "wikipediaUrl": "https://en.wikipedia.org/wiki/Tracy_Panton"
    },
    {
      "id": 48,
      "name": "Valerie Woods",
      "image": "http://commons.wikimedia.org/wiki/Special:FilePath/Valerie%20Woods%20CWP%20%28cropped%29.png",
      "sitelinks": 4,
      "birthYear": "1973",
      "deathYear": null,
      "occupation": "politician",
      "wikidataUrl": "http://www.wikidata.org/entity/Q97258252",
      "answerKey": "valerie woods",
      "wikipediaUrl": "https://en.wikipedia.org/wiki/Valerie_Woods"
    },
    {
      "id": 49,
      "name": "Carlos Perdomo",
      "image": "http://commons.wikimedia.org/wiki/Special:FilePath/Carlos%20Perdomo%20U.S.%20Embassy%20%28cropped%29.jpg",
      "sitelinks": 4,
      "birthYear": "1945",
      "deathYear": null,
      "occupation": "politician",
      "wikidataUrl": "http://www.wikidata.org/entity/Q5042485",
      "answerKey": "carlos perdomo",
      "wikipediaUrl": "https://en.wikipedia.org/wiki/Carlos_Perdomo"
    },
    {
      "id": 50,
      "name": "Elvin Penner",
      "image": "http://commons.wikimedia.org/wiki/Special:FilePath/The%20Minister%20of%20Sports%2C%20Mr.%20Elvin%20Penner%20receiving%20the%20Queen%27s%20Baton%202010%20from%20the%20Mayor%20of%20Belize%2C%20Ms.%20Zenida%20Moya%20Flowers%20on%20its%20arrival%20at%20the%20House%20of%20Culture%2C%20at%20Belize%20on%20April%2008%2C%202010.jpg",
      "sitelinks": 4,
      "birthYear": "1970",
      "deathYear": null,
      "occupation": "politician",
      "wikidataUrl": "http://www.wikidata.org/entity/Q5368083",
      "answerKey": "elvin penner",
      "wikipediaUrl": "https://en.wikipedia.org/wiki/Elvin_Penner"
    }
  ],
  "flag": "http://commons.wikimedia.org/wiki/Special:FilePath/Flag%20of%20Belize.svg",
  "updated": "2025-12-14T22:11:36.000Z",
  "wikipediaLinksAdded": true
}